{
  "user": {},
  "ptpt": null,
  "nextComment": {
    "txt": "原子力発電は最大限活用",
    "tid": 1,
    "created": "1728980432094",
    "tweet_id": null,
    "quote_src_url": null,
    "is_seed": true,
    "is_meta": false,
    "lang": null,
    "pid": 0,
    "randomN": 1.6655411184438482,
    "remaining": 8,
    "total": 8,
    "translations": []
  },
  "conversation": {
    "topic": "エネルギー政策",
    "description": "",
    "link_url": null,
    "parent_url": null,
    "upvotes": 1,
    "participant_count": 64,
    "is_anon": false,
    "is_active": true,
    "is_draft": true,
    "is_public": true,
    "is_data_open": false,
    "profanity_filter": true,
    "spam_filter": true,
    "strict_moderation": false,
    "prioritize_seed": false,
    "vis_type": 1,
    "write_type": 1,
    "help_type": 1,
    "write_hint_type": 1,
    "style_btn": null,
    "socialbtn_type": 0,
    "subscribe_type": 1,
    "branding_type": 1,
    "bgcolor": null,
    "help_bgcolor": null,
    "help_color": null,
    "email_domain": null,
    "use_xid_whitelist": false,
    "owner": 72,
    "org_id": 72,
    "context": null,
    "course_id": null,
    "owner_sees_participation_stats": false,
    "auth_needed_to_vote": false,
    "auth_needed_to_write": true,
    "auth_opt_fb": true,
    "auth_opt_tw": true,
    "auth_opt_allow_3rdparty": true,
    "modified": "1729304410475",
    "created": "1728980428991",
    "site_id": "polis_site_id_wlE61IMj5fRdvFgrn7",
    "auth_opt_fb_computed": true,
    "auth_opt_tw_computed": true,
    "translations": [],
    "ownername": "admin",
    "is_mod": false,
    "is_owner": false,
    "conversation_id": "3dzkftnmrm"
  },
  "votes": [],
  "pca": "{\"n\":64,\"pca\":{\"comps\":[[0.17723355305156713,-0.47308744615173287,0.3008872940091873,0.4996892288660974,-0.3264768323295637,0.4747638398445893,-0.19677678341433946,-0.18397042877202874],[0.6936825773012513,0.17832961566384853,0.5318587947723228,-0.0764943395489951,0.2777164398621031,0.04832224918359425,0.26658137092342665,0.218519519738895]],\"center\":[-0.32786885245901637,-0.3870967741935484,0.10714285714285711,0.11475409836065575,-0.6034482758620691,-0.25,-0.6166666666666667,-0.17543859649122803],\"comment-extremity\":[1.3611042420096167,0.8764527847548682,1.9135501533590358,1.59387448805573,0.4807457154672626,1.0123294153859361,0.35924977405627667,0.66619621676923],\"comment-projection\":[[-0.3369340941559674,0.820121739883123,-0.9422204035671101,-1.5755205030008133,0.36618217840912914,-1.0071261918488195,0.21335137016294584,0.4290580121373627],[-1.3187418905198511,-0.3091436812804727,-1.6655013961333751,0.24118670837958625,-0.31149166145448404,-0.10250697023971683,-0.28903562584754067,-0.509633811141264]]},\"tids\":[0,1,2,3,4,5,6,7],\"mod-in\":[0,7,1,4,6,3,2,5],\"n-cmts\":8,\"in-conv\":[0,62,7,20,58,60,27,1,24,55,39,46,4,54,15,48,50,31,32,40,33,13,22,36,41,43,61,29,44,6,28,51,25,34,17,3,12,2,23,47,35,19,57,11,9,5,14,45,53,26,16,38,30,10,18,52,42,63,8,49],\"mod-out\":[],\"repness\":{\"0\":[{\"tid\":3,\"p-test\":2.190890230020664,\"n-agree\":20,\"repness\":22.35483870967742,\"n-trials\":29,\"n-success\":20,\"p-success\":0.6774193548387097,\"best-agree\":true,\"repful-for\":\"agree\",\"repness-test\":5.499889},{\"tid\":5,\"p-test\":5.112077203381551,\"repness\":4.989247311827957,\"n-trials\":29,\"n-success\":28,\"p-success\":0.9354838709677419,\"repful-for\":\"agree\",\"repness-test\":6.1042404},{\"tid\":0,\"p-test\":1.4605934866804426,\"repness\":1.348387096774194,\"n-trials\":29,\"n-success\":18,\"p-success\":0.6129032258064516,\"repful-for\":\"agree\",\"repness-test\":1.3013642}],\"1\":[{\"tid\":1,\"p-test\":5.656854249492381,\"n-agree\":31,\"repness\":4.155844155844156,\"n-trials\":31,\"n-success\":31,\"p-success\":0.9696969696969697,\"best-agree\":true,\"repful-for\":\"agree\",\"repness-test\":6.1619754},{\"tid\":4,\"p-test\":5.112077203381551,\"repness\":1.611111111111111,\"n-trials\":29,\"n-success\":28,\"p-success\":0.9354838709677419,\"repful-for\":\"agree\",\"repness-test\":3.447051},{\"tid\":6,\"p-test\":4.242640687119286,\"repness\":1.643939393939394,\"n-trials\":31,\"n-success\":27,\"p-success\":0.8484848484848485,\"repful-for\":\"agree\",\"repness-test\":2.9619074},{\"tid\":3,\"p-test\":3.5355339059327378,\"repness\":12.21212121212121,\"n-trials\":31,\"n-success\":25,\"p-success\":0.7878787878787878,\"repful-for\":\"disagree\",\"repness-test\":5.897321},{\"tid\":5,\"p-test\":1.6164477182409738,\"repness\":19.375,\"n-trials\":30,\"n-success\":19,\"p-success\":0.625,\"repful-for\":\"disagree\",\"repness-test\":5.0280094}]},\"consensus\":{\"agree\":[{\"tid\":4,\"p-test\":4.296234062367186,\"n-trials\":58,\"n-success\":45,\"p-success\":0.7666666666666667},{\"tid\":6,\"p-test\":3.200921998322399,\"n-trials\":60,\"n-success\":42,\"p-success\":0.6935483870967742},{\"tid\":1,\"p-test\":1.8898223650461348,\"n-trials\":62,\"n-success\":38,\"p-success\":0.609375}],\"disagree\":[]},\"meta-tids\":[],\"votes-base\":{\"0\":{\"A\":[0,0,1,2,1,1,0,0,1,0,1,1,0,1,1,0,0,0,0,1,1,1,0,0,0,0,0,1,1,1,0,0,0,0,0,0,0,1,1,0,1,0,0,3,0,1,2,0,1,1,1,1,1,1,1],\"D\":[0,1,0,0,0,0,0,0,0,1,0,0,0,0,0,0,2,0,0,0,0,0,1,0,1,1,0,0,0,0,1,1,0,1,1,1,0,0,0,0,0,0,0,0,1,0,0,0,0,0,0,0,0,0,0],\"S\":[1,1,1,2,1,1,1,1,1,1,1,1,1,1,1,1,2,1,1,1,1,1,1,1,1,1,1,1,1,1,1,1,1,1,1,1,1,1,1,1,1,1,1,3,1,1,2,1,1,1,1,1,1,1,1]},\"1\":{\"A\":[0,1,1,0,0,0,1,0,1,1,0,1,1,0,1,1,2,1,1,1,1,0,0,0,0,1,0,1,0,0,1,1,0,1,1,0,1,0,1,1,1,0,1,3,1,0,2,0,0,1,1,1,1,1,0],\"D\":[0,0,0,2,0,1,0,1,0,0,1,0,0,0,0,0,0,0,0,0,0,1,1,1,0,0,1,0,1,0,0,0,0,0,0,0,0,0,0,0,0,1,0,0,0,1,0,1,0,0,0,0,0,0,0],\"S\":[1,1,1,2,1,1,1,1,1,1,1,1,1,0,1,1,2,1,1,1,1,1,1,1,1,1,1,1,1,1,1,1,1,1,1,1,1,1,1,1,1,1,1,3,1,1,2,1,1,1,1,1,1,1,1]},\"2\":{\"A\":[0,0,0,2,0,1,0,1,0,0,0,0,0,0,0,0,0,0,0,0,0,1,0,0,0,0,0,1,1,0,0,0,0,0,0,0,0,0,0,0,1,1,0,3,0,1,0,0,0,1,0,0,1,0,1],\"D\":[0,1,1,0,0,0,1,0,1,1,0,0,0,0,1,0,2,1,0,0,0,0,1,0,1,1,0,0,0,0,1,1,0,1,1,1,0,0,0,0,0,0,1,0,1,0,2,0,0,0,0,0,0,1,0],\"S\":[1,1,1,2,1,1,1,1,1,1,0,0,0,0,1,1,2,1,1,1,1,1,1,1,1,1,1,1,1,1,1,1,1,1,1,1,1,1,1,1,1,1,1,3,1,1,2,1,1,1,1,1,1,1,1]},\"3\":{\"A\":[0,0,0,2,0,1,0,1,0,0,1,0,0,1,0,0,0,0,0,0,0,1,1,1,1,0,1,0,1,1,0,0,0,0,1,1,0,1,0,0,0,1,0,0,0,1,0,0,0,0,1,0,1,0,0],\"D\":[0,1,1,0,0,0,1,0,0,1,0,1,1,0,0,0,2,1,0,0,1,0,0,0,0,1,0,0,0,0,1,1,0,1,0,0,1,0,0,1,1,0,1,3,1,0,2,0,0,1,0,0,0,1,0],\"S\":[1,1,1,2,1,1,1,1,1,1,1,1,1,1,1,1,2,1,1,1,1,1,1,1,1,1,1,1,1,1,1,1,1,1,1,1,1,1,1,1,1,1,1,3,1,1,2,1,1,1,1,1,1,1,1]},\"4\":{\"A\":[0,1,1,0,1,1,1,0,1,1,0,0,0,0,1,1,2,1,1,1,1,0,0,0,1,1,0,1,0,1,1,1,1,1,1,1,1,1,1,1,1,0,1,3,0,1,2,1,1,1,1,1,1,1,1],\"D\":[0,0,0,2,0,0,0,1,0,0,1,0,0,0,0,0,0,0,0,0,0,1,1,0,0,0,1,0,1,0,0,0,0,0,0,0,0,0,0,0,0,1,0,0,1,0,0,0,0,0,0,0,0,0,0],\"S\":[1,1,1,2,1,1,1,1,1,1,1,0,0,1,1,1,2,1,1,1,1,1,1,1,1,1,1,1,1,1,1,1,1,1,1,1,1,1,1,1,1,1,1,3,1,1,2,1,1,1,1,1,1,1,1]},\"5\":{\"A\":[0,0,0,2,1,1,0,1,0,0,1,0,0,1,1,1,0,0,0,1,0,1,1,1,1,0,1,1,1,1,1,0,1,0,1,1,0,1,0,0,1,1,0,0,0,1,0,1,1,1,1,0,1,1,1],\"D\":[0,1,1,0,0,0,1,0,1,0,0,0,1,0,0,0,2,0,0,0,1,0,0,0,0,1,0,0,0,0,0,0,0,1,0,0,1,0,1,0,0,0,1,3,1,0,2,0,0,0,0,0,0,0,0],\"S\":[1,1,1,2,1,1,1,1,1,1,1,0,1,1,1,1,2,1,1,1,1,1,1,1,1,1,1,1,1,1,1,1,1,1,1,1,1,1,1,1,1,1,1,3,1,1,2,1,1,1,1,1,1,1,1]},\"6\":{\"A\":[0,1,0,0,0,0,1,0,1,1,0,0,1,1,1,1,2,1,1,1,1,0,0,1,0,0,0,1,0,0,1,1,1,1,1,1,1,1,1,1,1,1,0,3,1,1,2,0,1,1,1,1,1,1,1],\"D\":[0,0,0,0,0,0,0,0,0,0,0,1,0,0,0,0,0,0,0,0,0,0,1,0,0,1,1,0,1,0,0,0,0,0,0,0,0,0,0,0,0,0,0,0,0,0,0,0,0,0,0,0,0,0,0],\"S\":[1,1,1,2,1,1,1,1,1,1,1,1,1,1,1,1,2,1,1,1,1,1,1,1,1,1,1,1,1,1,1,1,1,1,1,1,1,1,1,1,1,1,1,3,1,1,2,1,1,1,1,1,1,1,1]},\"7\":{\"A\":[0,0,0,0,0,0,0,0,0,0,1,0,0,0,0,1,2,1,1,0,1,0,1,1,1,0,0,0,1,0,1,1,1,0,0,0,1,0,1,1,0,0,1,3,0,1,2,0,0,1,0,1,1,0,1],\"D\":[0,0,1,2,1,1,1,1,1,0,0,1,0,0,0,0,0,0,0,0,0,0,0,0,0,0,1,1,0,0,0,0,0,0,1,1,0,1,0,0,1,0,0,0,1,0,0,0,0,0,1,0,0,1,0],\"S\":[1,1,1,2,1,1,1,1,1,1,1,1,0,0,1,1,2,1,1,1,1,1,1,1,1,1,1,1,1,1,1,1,1,0,1,1,1,1,1,1,1,1,1,3,1,1,2,1,1,1,1,1,1,1,1]}},\"group-votes\":{\"0\":{\"votes\":{\"0\":{\"A\":18,\"D\":4,\"S\":29},\"1\":{\"A\":6,\"D\":13,\"S\":28},\"2\":{\"A\":12,\"D\":4,\"S\":27},\"3\":{\"A\":20,\"D\":1,\"S\":29},\"4\":{\"A\":17,\"D\":9,\"S\":29},\"5\":{\"A\":28,\"D\":0,\"S\":29},\"6\":{\"A\":15,\"D\":3,\"S\":29},\"7\":{\"A\":9,\"D\":12,\"S\":28}},\"n-members\":29,\"id\":0},\"1\":{\"votes\":{\"0\":{\"A\":14,\"D\":9,\"S\":31},\"1\":{\"A\":31,\"D\":0,\"S\":31},\"2\":{\"A\":4,\"D\":18,\"S\":29},\"3\":{\"A\":0,\"D\":25,\"S\":31},\"4\":{\"A\":28,\"D\":1,\"S\":29},\"5\":{\"A\":5,\"D\":19,\"S\":30},\"6\":{\"A\":27,\"D\":2,\"S\":31},\"7\":{\"A\":19,\"D\":6,\"S\":29}},\"n-members\":31,\"id\":1}},\"base-clusters\":{\"x\":[-0.44654269247993705,2.00237228518714,1.2671579668976378,-2.882651315504703,-0.9560336818185586,-2.229697650845576,1.6411683033635445,-2.705417762453136,0.9642455214458796,1.527608445342551,-2.33221272188611,0.09969025081867904,1.8458846216243847,-1.4594650974093581,0.19868827052872978,0.25900495834313836,2.186342713959169,1.5343453210630127,0.7337687981877277,-0.1021990234804575,1.5309883138468472,-2.6986808867326744,-1.7552455472534767,-1.5133359951559884,-0.43242765302827674,1.6088187183584612,-2.6013072518582883,-0.5870567462616736,-2.711487241374985,-1.2717524819126271,1.2368150342699902,1.7115788741145797,-0.2140824878085945,2.1751299904677466,-0.13050428100626205,-0.6035917271579948,1.7082218668984144,-1.2589461272703164,1.03129908498075,1.2334580270538251,-0.08736751739557619,-2.324670550266768,1.8123323774932625,1.23010101983766,1.165448191755984,-1.6649800098871792,1.8318756078560348,-1.0679171461466956,-0.5752864696321904,0.2805733401484813,-0.7858586811185835,0.5565352451361605,-0.7188051175837133,0.5144070706227986,-0.692203334869349],\"y\":[0.6306575700143463,1.105399425273141,0.2031351613329603,0.10785386357101961,-0.1705441765937074,-0.4475790161531866,0.630236367710785,0.8015364408722708,0.01304812995852872,1.0570771760895468,0.2775866017576699,0.056375479589513826,0.010922632603243979,-0.44501720797447597,-0.3021158881475548,-0.3588116253575213,0.886879905534246,0.1448750790494007,-0.310489376173927,-0.8339746829198775,-1.032344043840579,-0.11066565616787537,2.388478939163804,0.352058385381274,1.3881350728523227,1.6385621671199944,1.59997660656802,-1.1473139579533052,-0.0626038049833437,-0.3125693567836073,0.7902354071670576,0.8385576563506518,-0.18048200969367273,1.1407379747767168,1.3802631257428377,1.5585927414066862,-0.3386614665393278,-0.36063120796813897,-0.9558497042915841,-0.3869837157229221,-1.2238082975023001,0.31643555020994923,0.45977869915642167,-1.5642028386129019,1.8793518247362422,-1.1511994265544032,-0.5004852490682563,0.48294849663249745,-0.655645067256029,-1.6608473369800902,-0.5389608236319875,-1.0041719534751783,-1.5078586578821003,-0.16009070795765484,-1.4060233817672467],\"id\":[0,1,2,3,4,5,6,7,8,9,10,11,12,13,14,15,16,17,18,19,20,21,22,23,24,26,27,28,29,30,31,32,33,34,35,36,37,38,39,41,42,43,44,45,46,47,48,49,50,51,52,53,54,55,56],\"count\":[1,1,1,2,1,1,1,1,1,1,1,1,1,1,1,1,2,1,1,1,1,1,1,1,1,1,1,1,1,1,1,1,1,1,1,1,1,1,1,1,1,1,1,3,1,1,2,1,1,1,1,1,1,1,1],\"members\":[[0],[17],[1],[7,8],[3],[2],[4],[5],[6],[10],[11],[12],[13],[14],[15],[16],[9,25],[18],[19],[20],[22],[23],[24],[26],[27],[28],[30],[32],[31],[33],[34],[35],[36],[38],[39],[40],[41],[42],[43],[45],[47],[46],[48],[29,49,63],[50],[51],[44,52],[55],[53],[54],[57],[58],[60],[61],[62]]},\"group-clusters\":[{\"id\":0,\"center\":[-1.3687027074173708,0.028879328481326214],\"members\":[0,3,4,5,7,10,13,19,21,22,23,24,27,28,29,30,33,35,36,38,42,43,47,49,50,52,54,56]},{\"id\":1,\"center\":[1.302138083261068,-0.014899736789640738],\"members\":[1,2,6,8,9,11,12,14,15,16,17,18,20,26,31,32,34,37,39,41,44,45,46,48,51,53,55]}],\"lastModTimestamp\":null,\"user-vote-counts\":{\"0\":8,\"1\":8,\"2\":8,\"3\":8,\"4\":8,\"5\":8,\"6\":8,\"7\":8,\"8\":8,\"9\":8,\"10\":8,\"11\":7,\"12\":5,\"13\":5,\"14\":5,\"15\":8,\"16\":8,\"17\":8,\"18\":8,\"19\":8,\"20\":8,\"21\":2,\"22\":8,\"23\":8,\"24\":8,\"25\":8,\"26\":8,\"27\":8,\"28\":8,\"29\":8,\"30\":8,\"31\":8,\"32\":8,\"33\":8,\"34\":8,\"35\":8,\"36\":8,\"37\":2,\"38\":7,\"39\":8,\"40\":8,\"41\":8,\"42\":8,\"43\":8,\"44\":8,\"45\":8,\"46\":8,\"47\":8,\"48\":8,\"49\":8,\"50\":8,\"51\":8,\"52\":8,\"53\":8,\"54\":8,\"55\":8,\"56\":1,\"57\":8,\"58\":8,\"59\":1,\"60\":8,\"61\":8,\"62\":8,\"63\":8},\"lastVoteTimestamp\":1729304410475,\"comment-priorities\":{\"0\":0.872774233564341,\"1\":0.9594227869292603,\"2\":0.33197760066154414,\"3\":0.4554905482162188,\"4\":1.1284525487481483,\"5\":0.9539704574366069,\"6\":0.5347440674837478,\"7\":0.42815745606889183},\"group-aware-consensus\":{\"0\":0.27859237536656895,\"1\":0.22626262626262628,\"2\":0.07230255839822024,\"3\":0.020527859237536656,\"4\":0.5431841831425598,\"5\":0.1754032258064516,\"6\":0.43792766373411535,\"7\":0.2150537634408602},\"math_tick\":1606}",
  "famous": {},
  "acceptLanguage": "en-US"
}